Workbook
Name ListaCBO: OFFSET('Tabela CBO'!$D$3, 0, 0, COUNTIF('Tabela CBO'!$D$3:$D$100, "?*"), 1)

Sheet Simulador  IR 2024
A1: Tabela progressiva do IR - Ano 2024 | E1: Revisão 7 - 13/05/2025 | J1: Tabela IR 2024
A3: De | B3: Até | C3: Alíquota | D3: Dedução | H3: Simulador IR do contracheque (preencher somente as células azuis):
B4: 2259.2 | C4: 0 | D4: 0
A5: 2259.21 | B5: 2826.65 | C5: 7.5 | D5: 169.44 | I5: Rendimentos tributáveis: | L5: 0
A6: 2826.66 | B6: 3751.05 | C6: 15 | D6: 381.44 | I6: Contribuição previdenciária: | L6: 0
A7: 3751.06 | B7: 4664.68 | C7: 22.5 | D7: 662.77 | I7: Número de dependentes: | L7: 0 | M7: Dedução total de dependentes: | P7: =L7*D10 -> 0
A8: 4664.68 | C8: 27.5 | D8: 896 | I8: Base de cálculo do IR: | L8: =L5-L6-P7 -> 0
I9: Valor do IR: | J9: =IF(L8<=$B$4,0,IF(AND(L8>=$A$5,L8<=$B$5),TRUNC(L8*$C$5/100-$D$5,2),IF(AND(L8>=$A$6,L8<=$B$6),TRUNC(L8*$C$6/100-$D$6,2),IF(AND(L8>=$A$7,L8<=$B$7),TRUNC(L8*$C$7/100-$D$7,2),IF(L8>=$A$8,TRUNC(L8*$C$8/100-$D$8,2),""))))) -> 0 | L9: Tem que coincidir com o valor calculado no contracheque
A10: Valor por dependente | D10: 189.59 | I10: Valor Líquido: | J10: =L5-L6-J9 -> 0
H11: Cálculo da retenção da bolsa de servidor (preencher somente o valor da bolsa)
I13: Valor da bolsa: | J13: 0 | L13: INSS bolsa: | M13: =TRUNC(J13*0.11,2) -> 0 | N13: =IF(AND(TRUNC(J13*0.11,2)+L6<564.8,J13<>"",J13>0),564.8,IF(AND(TRUNC(J13*0.11,2)+L6>=564.8,J13<>"",J13>0),TRUNC(J13*0.11,2)+L6,"")) | O13: INSS Patronal: | Q13: =TRUNC(J13*0.2,2) -> 0
I15: Rendimentos tributáveis+bolsa: | L15: =L5+J13 -> 0
I16: Contribuição previdenciária: | L16: =N13
I17: Número de dependentes: | L17: =L7 -> 0 | M17: Dedução total de dependentes: | P17: =L17*D10 -> 0
I18: Base de cálculo do IR: | L18: =IF(AND(J13<>"",J13<>0),L15-L16-P17,"")
I19: Base de cálculo IR para o SIAFI: | L19: =J13-M13 -> 0 | M19: lançar a base de cálculo na dedução do SIAFI - DDF009
I20: Valor do IR: | J20: =IF(AND(J13<>"",J13<>0),IF(L18<=$B$4,0,IF(AND(L18>=$A$5,L18<=$B$5),TRUNC(L18*$C$5/100-$D$5,2),IF(AND(L18>=$A$6,L18<=$B$6),TRUNC(L18*$C$6/100-$D$6,2),IF(AND(L18>=$A$7,L18<=$B$7),TRUNC(L18*$C$7/100-$D$7,2),IF(L18>=$A$8,TRUNC(L18*$C$8/100-$D$8,2),"")))))-J9,"") | L20: Valor a ser lançado na retenção de IR da liquidação da bolsa - DDF009

Sheet Simulador IR 2025
A1: Tabela I - progressiva do IR - Ano 2026 | E1: Revisão 14.2026.1 - 24/07/2026 | J1: Tabela IR 2026
A2: Para Rend. Tributáveis acima de R$ 7.350,00 | V2: Cálculo do IR - 2026
A3: De | B3: Até | C3: Alíquota | D3: Dedução | H3: Simulador IR do contracheque do servidor (preencher somente as células azuis): | V3: Rendimentos Tributáveis
B4: 2428.8 | C4: 0 | D4: 0 | V4: Até R$ 5.000,00 | W4: Entre R$ 5.000,01 e R$ 7.350,00 | X4: Acima de R$ 7.350,00 - Tabela I
A5: 2428.81 | B5: 2826.65 | C5: 7.5 | D5: 182.16 | I5: Rendimentos tributáveis: | U5: IR: | V5: 0 | W5: =$X$5-$W$8 -> #VALUE! | X5: =IF(L8<=$B$4,0,IF(AND(L8>=$A$5,L8<=$B$5),TRUNC(L8*$C$5/100-$D$5,2),IF(AND(L8>=$A$6,L8<=$B$6),TRUNC(L8*$C$6/100-$D$6,2),IF(AND(L8>=$A$7,L8<=$B$7),TRUNC(L8*$C$7/100-$D$7,2),IF(L8>=$A$8,TRUNC(L8*$C$8/100-$D$8,2),""))))) -> #VALUE!
A6: 2826.66 | B6: 3751.05 | C6: 15 | D6: 394.16 | I6: Contribuição previdenciária: | N6: Contribuição prev. considerada | Q6: =IF(L6+P7<C11,C11,L6+P7) -> 607.2
A7: 3751.06 | B7: 4664.68 | C7: 22.5 | D7: 675.49 | I7: Número de dependentes: | M7: Dedução total de dependentes: | P7: =L7*D10 -> 0 | W7: Cálculo da redução *
A8: 4664.68 | C8: 27.5 | D8: 908.73 | I8: Base de cálculo do IR: | L8: =IF(AND(L5>0,L6>0),L5-Q6,"") | W8: =IF(AND(L5>5000,L5<=7350),978.62-(0.133145*L5),0) -> 0
I9: Valor do IR: | J9: =IF(L5<=5000,V5,IF(AND(L5>5000,L5<=7350),W5,X5)) -> 0 | L9: Tem que coincidir com o valor calculado no contracheque,
A10: Valor por dependente | D10: 189.59 | I10: Valor Líquido: | J10: =L5-L6-J9 -> 0 | L10: podendo ocorrer diferença de um centavo devido a arredondamentos! | W10: *R$ 978,62 - (0,133145 * Rendimentos Tributáveis)
A11: Desconto simplificado | C11: 607.2 | H11: Cálculo da retenção da bolsa de servidor (preencher somente o valor da bolsa)
A13: Medida Provisória 1.294 de 11 de abril de 2025 | I13: Valor da bolsa: | L13: INSS bolsa: | M13: =TRUNC(J13*0.11,2) -> 0 | N13: =IF(AND(TRUNC(J13*0.11,2)+Q6<C11,J13<>"",J13>0),C11,IF(AND(TRUNC(J13*0.11,2)+Q6>=C11,J13<>"",J13>0),TRUNC(J13*0.11,2)+Q6,"")) | O13: INSS Patronal: | Q13: =TRUNC(J13*0.2,2) -> 0 | V13: Cálculo do IR - 2026 - Exclusivo para a bolsa
V14: Rendimentos Tributáveis
I15: Rendimentos tributáveis+bolsa: | L15: =L5+J13 -> 0 | V15: Até R$ 5.000,00 | W15: Entre R$ 5.000,01 e R$ 7.350,00 | X15: Acima de R$ 7.350,00 - Tabela I
I16: Contribuição previdenciária: | L16: =IF(L6+M13<C11,C11,L6+M13) -> 607.2 | T16: IR para bolsas: | V16: 0 | W16: =$X$16-W19 -> #VALUE! | X16: =IF(AND(J13<>"",J13<>0),IF(L18<=$B$4,0,IF(AND(L18>=$A$5,L18<=$B$5),TRUNC(L18*$C$5/100-$D$5,2),IF(AND(L18>=$A$6,L18<=$B$6),TRUNC(L18*$C$6/100-$D$6,2),IF(AND(L18>=$A$7,L18<=$B$7),TRUNC(L18*$C$7/100-$D$7,2),IF(L18>=$A$8,TRUNC(L18*$C$8/100-$D$8,2),"")))))-J9,"")
I17: Número de dependentes: | L17: =L7 -> 0 | M17: Dedução total de dependentes: | P17: =L17*D10 -> 0
I18: Base de cálculo do IR: | L18: =IF(AND(J13<>"",J13<>0),L15-L16-P17,"") | W18: Cálculo da redução *
I19: Base de cálculo IR para o SIAFI: | L19: =J13-M13 -> 0 | M19: lançar a base de cálculo na dedução do SIAFI - DDF054 | W19: =IF(AND(L15>5000,L15<=7350),978.62-(0.133145*L15),0) -> 0
I20: Valor do IR: | L20: =IF(AND(L5<>0,L6<>0),IF(L15<=5000,V16,IF(AND(L15>5000,L15<=7350),W16,X16)),0) -> 0 | M20: Valor a ser lançado na retenção de IR da liquidação da bolsa - DDF054
A21: A partir de 1º de maio/2025 | I21: Valor Líquido: | L21: =J13-M13-L20 -> 0 | W21: *R$ 978,62 - (0,133145 * Rendimentos Tributáveis)
H23: Criada por José Rodrigues - CFCA - Reitoria - Março/2025 - Última atualização: Julho/2026
G25: Servidor: | L25: CPF: | O25: Processo SEI:
G27: Data de nascimento: | L27: Banco (código): | N27: Agência: | P27: Conta:
L28: (3 dígitos) | N28: (4 dígitos sem o verificador)
G29: CBO:
I30: (digite o código, tecle ENTER e volte a célula para selecionar a descrição na seta. Apenas para fins de validação do código.)

Sheet Controle de revisão
A1: Data | B1: Versão | C1: Alteração
A2: 46043 | B2: 13.2026.1 | C2: Adequação da planilha para a nova metodologia de cálculo do IR para 2026
A3: 46046 | B3: 13.2026.2 | C3: Algumas validações adicionais nas fórmulas das células M21 e Q21
C4: Campo de referência para informação do nome do servidor/colaborador - G24
A5: 46052 | B5: 13.2026.3 | C5: Retirei o cálculo do valor para colaborador, pois envolve outras análises, que não são o foco principal desta planilha
A6: 46056 | B6: 13.2026.4 | C6: Inclusão da célula do líquido a pagar para a bolsa, L21
A7: 46212 | B7: 13.2026.5 | C7: Correção nas observações em vermelho, de DDF009 para DDF054
A8: 46227 | B8: 14.2026.0 | C8: Separação dos campos para digitação de nome, CPF e processo SEI. Inclusão do campo para data de nascimento e inclusão do campo para CBO (com validação de código via seleção de lista)
A9: 46251 | B9: 14.2026.1 | C9: Inclusão de células para dados bancários

Sheet Tabela CBO
A1: CLASSIFICAÇÃO BRASILEIRA DE OCUPAÇÃO (CBO)
A2: CÓDIGO/TÍTULO
A3: 10105 Oficial general da aeronáutica | B3: =IFERROR(FIND('Simulador IR 2025'!$I$29, A3), 0) -> 1 | C3: =IF(B3>0, MAX($C$2:C2)+1, "") -> 1 | D3: =IFERROR(INDEX($A$3:$A$4999, MATCH(ROW(A1), $C$3:$C$4999, 0)), "") -> 10105 Oficial general da aeronáutica
A4: 10110 Oficial general do exército | B4: =IFERROR(FIND('Simulador IR 2025'!$I$29, A4), 0) -> 1 | C4: =IF(B4>0, MAX($C$2:C3)+1, "") -> 2 | D4: =IFERROR(VLOOKUP(ROW(A2), $A$3:$C$2681, -2, FALSE), "")
A5: 10115 Oficial general da marinha | B5: =IFERROR(FIND('Simulador IR 2025'!$I$29, A5), 0) -> 1 | C5: =IF(B5>0, MAX($C$2:C4)+1, "") -> 3 | D5: =IFERROR(VLOOKUP(ROW(A3), $A$3:$C$2681, -2, FALSE), "")
A6: 10205 Oficial da aeronáutica | B6: =IFERROR(FIND('Simulador IR 2025'!$I$29, A6), 0) -> 1 | C6: =IF(B6>0, MAX($C$2:C5)+1, "") -> 4 | D6: =IFERROR(VLOOKUP(ROW(A4), $A$3:$C$2681, -2, FALSE), "")
A7: 10210 Oficial do exército | B7: =IFERROR(FIND('Simulador IR 2025'!$I$29, A7), 0) -> 1 | C7: =IF(B7>0, MAX($C$2:C6)+1, "") -> 5 | D7: =IFERROR(VLOOKUP(ROW(A5), $A$3:$C$2681, -2, FALSE), "")
A8: 10215 Oficial da marinha | B8: =IFERROR(FIND('Simulador IR 2025'!$I$29, A8), 0) -> 1 | C8: =IF(B8>0, MAX($C$2:C7)+1, "") -> 6 | D8: =IFERROR(VLOOKUP(ROW(A6), $A$3:$C$2681, -2, FALSE), "")
A9: 10305 Praça da aeronáutica | B9: =IFERROR(FIND('Simulador IR 2025'!$I$29, A9), 0) -> 1 | C9: =IF(B9>0, MAX($C$2:C8)+1, "") -> 7 | D9: =IFERROR(VLOOKUP(ROW(A7), $A$3:$C$2681, -2, FALSE), "")
A10: 10310 Praça do exército | B10: =IFERROR(FIND('Simulador IR 2025'!$I$29, A10), 0) -> 1 | C10: =IF(B10>0, MAX($C$2:C9)+1, "") -> 8 | D10: =IFERROR(VLOOKUP(ROW(A8), $A$3:$C$2681, -2, FALSE), "")
A11: 10315 Praça da marinha | B11: =IFERROR(FIND('Simulador IR 2025'!$I$29, A11), 0) -> 1 | C11: =IF(B11>0, MAX($C$2:C10)+1, "") -> 9 | D11: =IFERROR(VLOOKUP(ROW(A9), $A$3:$C$2681, -2, FALSE), "")
A12: 20105 Coronel da polícia militar | B12: =IFERROR(FIND('Simulador IR 2025'!$I$29, A12), 0) -> 1 | C12: =IF(B12>0, MAX($C$2:C11)+1, "") -> 10 | D12: =IFERROR(VLOOKUP(ROW(A10), $A$3:$C$2681, -2, FALSE), "")
A13: 20110 Tenente-coronel da polícia militar | B13: =IFERROR(FIND('Simulador IR 2025'!$I$29, A13), 0) -> 1 | C13: =IF(B13>0, MAX($C$2:C12)+1, "") -> 11 | D13: =IFERROR(VLOOKUP(ROW(A11), $A$3:$C$2681, -2, FALSE), "")
A14: 20115 Major da polícia militar | B14: =IFERROR(FIND('Simulador IR 2025'!$I$29, A14), 0) -> 1 | C14: =IF(B14>0, MAX($C$2:C13)+1, "") -> 12 | D14: =IFERROR(VLOOKUP(ROW(A12), $A$3:$C$2681, -2, FALSE), "")
A15: 20205 Capitão da polícia militar | B15: =IFERROR(FIND('Simulador IR 2025'!$I$29, A15), 0) -> 1 | C15: =IF(B15>0, MAX($C$2:C14)+1, "") -> 13 | D15: =IFERROR(VLOOKUP(ROW(A13), $A$3:$C$2681, -2, FALSE), "")
... A2681: 992225 Auxiliar geral de conservação de vias permanentes (exceto trilhos) | B2681: =IFERROR(FIND('Simulador IR 2025'!$I$29, A2681), 0) -> 1 | C2681: =IF(B2681>0, MAX($C$2:C2680)+1, "") -> 2679 | D2681: =IFERROR(VLOOKUP(ROW(A2679), $A$3:$C$2681, -2, FALSE), "")
A2682: Digite o CBO | B2682: =IFERROR(FIND('Simulador IR 2025'!$I$29, A2682), 0) -> 1 | C2682: =IF(B2682>0, MAX($C$2:C2681)+1, "") -> 2680

Sheet Plan1
